[
    {
      "id": "1",
      "title": "Овен",
      "image": ""
    },
    {
        "id": "2",
        "title": "Телец",
        "image": ""
      },
      {
        "id": "3",
        "title": "Близнецы",
        "image": ""
      },
      {
        "id": "4",
        "title": "Рак",
        "image": ""
      },
      {
        "id": "5",
        "title": "Лев",
        "image": ""
      },
      {
        "id": "6",
        "title": "Дева",
        "image": ""
      },
      {
        "id": "7",
        "title": "Весы",
        "image": ""
      },
      {
        "id": "8",
        "title": "Скорпион",
        "image": ""
      },
      {
        "id": "9",
        "title": "Стрелец",
        "image": ""
      },
      {
        "id": "10",
        "title": "Козерог",
        "image": "img/Capricorn-PNG-File.png"
      },
      {
        "id": "11",
        "title": "Водолей",
        "image": ""
      },
      {
        "id": "12",
        "title": "Рыбы",
        "image": ""
      }
]